{"type":"files","data":[{"type":"file","data":{"id":"mwb8vfmswezsyvde","project_id":"psqe63yjva5xr44r","label":"선형 회귀 계수 및 빈도 분석","contents":{"mid":"mwb8vfmswezsyvde","type":"data","title":"선형 회귀 계수 및 빈도 분석","functions":[{"persist-mode":"auto","func":"brightics.function.io$load13889","name":"brightics.function.io$load","param":{"partial_path":["/brightics@samsung.com/upload/48_py_equip_on.csv"]},"display":{"label":"Load : equip_on","diagram":{"position":{"x":20,"y":120}},"sheet":{"out":{"partial":[{"panel":[{"id":"default-1546849792985","chartOption":{"colorSet":["#FD026C","#4682B8","#A5D22D","#F5CC0A","#FE8C01","#6B9494","#B97C46","#84ACD0","#C2E173","#F9DD5B","#FE569D","#FEB356","#9CB8B8","#D0A884","#2E6072","#6D8C1E","#A48806","#A90148","#A95E01","#476363","#7B532F"],"title":{"show":true,"text":"","subtext":"","rotate":0,"textStyle":{"color":"#000000","fontSize":12,"fontFamily":""},"subtextStyle":{"color":"#000000","fontSize":12,"fontFamily":""},"left":"50%","top":"0px"},"toolbar":{"show":false,"right":"8px","top":"8px","orientation":"horizontal","menu":{}},"chart":{"border":"1px #000000 none","background":"rgba(255, 255, 255,1)","animationDuration":1000,"type":"table"},"tooltip":{"triggerOn":"mousemove"},"grid":{"left":"10%","right":"10%","top":"60px","bottom":"60px","width":"auto","height":"auto"},"xAxis":[{"selected":[],"title":{"show":true,"text":"","subtext":"","rotate":0,"textStyle":{"color":"#000000","fontSize":12,"fontFamily":""},"subtextStyle":{"color":"#000000","fontSize":12,"fontFamily":""},"left":"50%","bottom":"5px"},"axisTick":{"show":true},"axisLine":{"onZero":false},"scale":true,"axisLabel":{"show":true,"rotate":0,"textStyle":{"color":"#000000","fontSize":12,"fontFamily":""}},"zlevel":1}],"yAxis":[{"selected":[],"title":{"show":true,"text":"","subtext":"","rotate":-90,"textStyle":{"color":"#000000","fontSize":12,"fontFamily":""},"subtextStyle":{"color":"#000000","fontSize":12,"fontFamily":""},"left":"8px","top":"50%"},"axisTick":{"show":true},"axisLine":{"onZero":false},"scale":true,"axisLabel":{"show":true,"rotate":0,"textStyle":{"color":"#000000","fontSize":12,"fontFamily":""}},"zlevel":1}],"colorBy":[{"selected":[]}],"legend":{"show":true,"orientation":"horizontal","left":"50%","right":"auto","top":"10px","bottom":"auto","textStyle":{"color":"#000000","fontSize":12,"fontFamily":"","fontStyle":"normal","fontWeight":"normal","fontDecoration":"none"}},"noDataMessage":"","plotOptions":{"table":{"formatter":[]},"map":{"geoData":{}}},"source":{"dataType":"lazy","lazyData":[]},"guide":{"message":"Set data options using Chart Setting Button."}},"dataSource":{"selectable":true},"style":{},"group":"w8xsr5ctfzyfndyfv2mjd6bc"}],"layout":{"type":"panel","id":"default-1546849792985"}}],"full":[{"panel":[],"layout":{}}]}},"description":""},"meta":{"table":{"type":"table"}},"context":"python","version":"3.6","outputs":{"table":"tcycsgn8gbatwm2d"},"fid":"fsrq3rteaup3j3w2"},{"persist-mode":"auto","func":"brightics.function.io$load13889","name":"brightics.function.io$load","param":{"partial_path":["/brightics@samsung.com/upload/48_py_power.csv"]},"display":{"label":"Load : power","diagram":{"position":{"x":20,"y":220}},"sheet":{"out":{"partial":[{"panel":[{"id":"default-1546849800584","chartOption":{"colorSet":["#FD026C","#4682B8","#A5D22D","#F5CC0A","#FE8C01","#6B9494","#B97C46","#84ACD0","#C2E173","#F9DD5B","#FE569D","#FEB356","#9CB8B8","#D0A884","#2E6072","#6D8C1E","#A48806","#A90148","#A95E01","#476363","#7B532F"],"title":{"show":true,"text":"","subtext":"","rotate":0,"textStyle":{"color":"#000000","fontSize":12,"fontFamily":""},"subtextStyle":{"color":"#000000","fontSize":12,"fontFamily":""},"left":"50%","top":"0px"},"toolbar":{"show":false,"right":"8px","top":"8px","orientation":"horizontal","menu":{}},"chart":{"border":"1px #000000 none","background":"rgba(255, 255, 255,1)","animationDuration":1000,"type":"table"},"tooltip":{"triggerOn":"mousemove"},"grid":{"left":"10%","right":"10%","top":"60px","bottom":"60px","width":"auto","height":"auto"},"xAxis":[{"selected":[],"title":{"show":true,"text":"","subtext":"","rotate":0,"textStyle":{"color":"#000000","fontSize":12,"fontFamily":""},"subtextStyle":{"color":"#000000","fontSize":12,"fontFamily":""},"left":"50%","bottom":"5px"},"axisTick":{"show":true},"axisLine":{"onZero":false},"scale":true,"axisLabel":{"show":true,"rotate":0,"textStyle":{"color":"#000000","fontSize":12,"fontFamily":""}},"zlevel":1}],"yAxis":[{"selected":[],"title":{"show":true,"text":"","subtext":"","rotate":-90,"textStyle":{"color":"#000000","fontSize":12,"fontFamily":""},"subtextStyle":{"color":"#000000","fontSize":12,"fontFamily":""},"left":"8px","top":"50%"},"axisTick":{"show":true},"axisLine":{"onZero":false},"scale":true,"axisLabel":{"show":true,"rotate":0,"textStyle":{"color":"#000000","fontSize":12,"fontFamily":""}},"zlevel":1}],"colorBy":[{"selected":[]}],"legend":{"show":true,"orientation":"horizontal","left":"50%","right":"auto","top":"10px","bottom":"auto","textStyle":{"color":"#000000","fontSize":12,"fontFamily":"","fontStyle":"normal","fontWeight":"normal","fontDecoration":"none"}},"noDataMessage":"","plotOptions":{"table":{"formatter":[]},"map":{"geoData":{}}},"source":{"dataType":"lazy","lazyData":[]},"guide":{"message":"Set data options using Chart Setting Button."}},"dataSource":{"selectable":true},"style":{},"group":"kuh5xspaj3b9yvrye979cyv8"}],"layout":{"type":"panel","id":"default-1546849800584"}}],"full":[{"panel":[],"layout":{}}]}},"description":""},"meta":{"table":{"type":"table"}},"context":"python","version":"3.6","outputs":{"table":"t7qvcgmf6phamzq6"},"fid":"f6ufkxbgp48yr86y"},{"persist-mode":"auto","func":"brightics.function.transform$pivot","name":"brightics.function.transform$pivot","param":{"aggfunc":["mean"],"values":["on"],"columns":["sensor"],"index":["timestamp"]},"display":{"label":"Pivot","diagram":{"position":{"x":270,"y":120}},"sheet":{"in":{"partial":[{"panel":[{"id":"default-1546850262524","chartOption":{"colorSet":["#FD026C","#4682B8","#A5D22D","#F5CC0A","#FE8C01","#6B9494","#B97C46","#84ACD0","#C2E173","#F9DD5B","#FE569D","#FEB356","#9CB8B8","#D0A884","#2E6072","#6D8C1E","#A48806","#A90148","#A95E01","#476363","#7B532F"],"title":{"show":true,"text":"","subtext":"","rotate":0,"textStyle":{"color":"#000000","fontSize":12,"fontFamily":""},"subtextStyle":{"color":"#000000","fontSize":12,"fontFamily":""},"left":"50%","top":"0px"},"toolbar":{"show":false,"right":"8px","top":"8px","orientation":"horizontal","menu":{}},"chart":{"border":"1px #000000 none","background":"rgba(255, 255, 255,1)","animationDuration":1000,"type":"table"},"tooltip":{"triggerOn":"mousemove"},"grid":{"left":"10%","right":"10%","top":"60px","bottom":"60px","width":"auto","height":"auto"},"xAxis":[{"selected":[],"title":{"show":true,"text":"","subtext":"","rotate":0,"textStyle":{"color":"#000000","fontSize":12,"fontFamily":""},"subtextStyle":{"color":"#000000","fontSize":12,"fontFamily":""},"left":"50%","bottom":"5px"},"axisTick":{"show":true},"axisLine":{"onZero":false},"scale":true,"axisLabel":{"show":true,"rotate":0,"textStyle":{"color":"#000000","fontSize":12,"fontFamily":""}},"zlevel":1}],"yAxis":[{"selected":[],"title":{"show":true,"text":"","subtext":"","rotate":-90,"textStyle":{"color":"#000000","fontSize":12,"fontFamily":""},"subtextStyle":{"color":"#000000","fontSize":12,"fontFamily":""},"left":"8px","top":"50%"},"axisTick":{"show":true},"axisLine":{"onZero":false},"scale":true,"axisLabel":{"show":true,"rotate":0,"textStyle":{"color":"#000000","fontSize":12,"fontFamily":""}},"zlevel":1}],"colorBy":[{"selected":[]}],"legend":{"show":true,"orientation":"horizontal","left":"50%","right":"auto","top":"10px","bottom":"auto","textStyle":{"color":"#000000","fontSize":12,"fontFamily":"","fontStyle":"normal","fontWeight":"normal","fontDecoration":"none"}},"noDataMessage":"","plotOptions":{"table":{"formatter":[]},"map":{"geoData":{}}},"source":{"dataType":"lazy","lazyData":[]},"guide":{"message":"Set data options using Chart Setting Button."}},"dataSource":{"selectable":true},"style":{},"group":"c8y2jj9a78u9cjczab38t4gq"}],"layout":{"type":"panel","id":"default-1546850262524"}}],"full":[{"panel":[],"layout":{}}]},"out":{"partial":[{"panel":[{"id":"default-1546850262660","chartOption":{"colorSet":["#FD026C","#4682B8","#A5D22D","#F5CC0A","#FE8C01","#6B9494","#B97C46","#84ACD0","#C2E173","#F9DD5B","#FE569D","#FEB356","#9CB8B8","#D0A884","#2E6072","#6D8C1E","#A48806","#A90148","#A95E01","#476363","#7B532F"],"title":{"show":true,"text":"","subtext":"","rotate":0,"textStyle":{"color":"#000000","fontSize":12,"fontFamily":""},"subtextStyle":{"color":"#000000","fontSize":12,"fontFamily":""},"left":"50%","top":"0px"},"toolbar":{"show":false,"right":"8px","top":"8px","orientation":"horizontal","menu":{}},"chart":{"border":"1px #000000 none","background":"rgba(255, 255, 255,1)","animationDuration":1000,"type":"table"},"tooltip":{"triggerOn":"mousemove"},"grid":{"left":"10%","right":"10%","top":"60px","bottom":"60px","width":"auto","height":"auto"},"xAxis":[{"selected":[],"title":{"show":true,"text":"","subtext":"","rotate":0,"textStyle":{"color":"#000000","fontSize":12,"fontFamily":""},"subtextStyle":{"color":"#000000","fontSize":12,"fontFamily":""},"left":"50%","bottom":"5px"},"axisTick":{"show":true},"axisLine":{"onZero":false},"scale":true,"axisLabel":{"show":true,"rotate":0,"textStyle":{"color":"#000000","fontSize":12,"fontFamily":""}},"zlevel":1}],"yAxis":[{"selected":[],"title":{"show":true,"text":"","subtext":"","rotate":-90,"textStyle":{"color":"#000000","fontSize":12,"fontFamily":""},"subtextStyle":{"color":"#000000","fontSize":12,"fontFamily":""},"left":"8px","top":"50%"},"axisTick":{"show":true},"axisLine":{"onZero":false},"scale":true,"axisLabel":{"show":true,"rotate":0,"textStyle":{"color":"#000000","fontSize":12,"fontFamily":""}},"zlevel":1}],"colorBy":[{"selected":[]}],"legend":{"show":true,"orientation":"horizontal","left":"50%","right":"auto","top":"10px","bottom":"auto","textStyle":{"color":"#000000","fontSize":12,"fontFamily":"","fontStyle":"normal","fontWeight":"normal","fontDecoration":"none"}},"noDataMessage":"","plotOptions":{"table":{"formatter":[]},"map":{"geoData":{}}},"source":{"dataType":"lazy","lazyData":[]},"guide":{"message":"Set data options using Chart Setting Button."}},"dataSource":{"selectable":true},"style":{},"group":"8kx7gju88czd3m5e5d56fweh"}],"layout":{"type":"panel","id":"default-1546850262660"}}],"full":[{"panel":[],"layout":{}}]}}},"meta":{"table":{"type":"table"},"out_table":{"type":"table"}},"context":"python","version":"3.6","inputs":{"table":"tcycsgn8gbatwm2d"},"outputs":{"out_table":"t47qszvdcvrpr5u8"},"fid":"f7kjjwjnkqw2mcg2"},{"persist-mode":"auto","func":"addColumnPython","name":"brightics.function.extraction$add_expression_column","context":"python","version":"3.6","param":{"expr_type":"sqlite","new_cols":["time"],"formulas":["strftime('%Y-%m-%d %H:%M:%S',timestamp)"]},"inputs":{"table":"t7qvcgmf6phamzq6"},"outputs":{"out_table":"tdckugyuhjysm8y5"},"meta":{"table":{"type":"table"},"out_table":{"type":"table"}},"display":{"label":"Add Function Column","diagram":{"position":{"x":270,"y":220}},"sheet":{"in":{"partial":[{"panel":[{"id":"default-1546850645288","chartOption":{"colorSet":["#FD026C","#4682B8","#A5D22D","#F5CC0A","#FE8C01","#6B9494","#B97C46","#84ACD0","#C2E173","#F9DD5B","#FE569D","#FEB356","#9CB8B8","#D0A884","#2E6072","#6D8C1E","#A48806","#A90148","#A95E01","#476363","#7B532F"],"title":{"show":true,"text":"","subtext":"","rotate":0,"textStyle":{"color":"#000000","fontSize":12,"fontFamily":""},"subtextStyle":{"color":"#000000","fontSize":12,"fontFamily":""},"left":"50%","top":"0px"},"toolbar":{"show":false,"right":"8px","top":"8px","orientation":"horizontal","menu":{}},"chart":{"border":"1px #000000 none","background":"rgba(255, 255, 255,1)","animationDuration":1000,"type":"table"},"tooltip":{"triggerOn":"mousemove"},"grid":{"left":"10%","right":"10%","top":"60px","bottom":"60px","width":"auto","height":"auto"},"xAxis":[{"selected":[],"title":{"show":true,"text":"","subtext":"","rotate":0,"textStyle":{"color":"#000000","fontSize":12,"fontFamily":""},"subtextStyle":{"color":"#000000","fontSize":12,"fontFamily":""},"left":"50%","bottom":"5px"},"axisTick":{"show":true},"axisLine":{"onZero":false},"scale":true,"axisLabel":{"show":true,"rotate":0,"textStyle":{"color":"#000000","fontSize":12,"fontFamily":""}},"zlevel":1}],"yAxis":[{"selected":[],"title":{"show":true,"text":"","subtext":"","rotate":-90,"textStyle":{"color":"#000000","fontSize":12,"fontFamily":""},"subtextStyle":{"color":"#000000","fontSize":12,"fontFamily":""},"left":"8px","top":"50%"},"axisTick":{"show":true},"axisLine":{"onZero":false},"scale":true,"axisLabel":{"show":true,"rotate":0,"textStyle":{"color":"#000000","fontSize":12,"fontFamily":""}},"zlevel":1}],"colorBy":[{"selected":[]}],"legend":{"show":true,"orientation":"horizontal","left":"50%","right":"auto","top":"10px","bottom":"auto","textStyle":{"color":"#000000","fontSize":12,"fontFamily":"","fontStyle":"normal","fontWeight":"normal","fontDecoration":"none"}},"noDataMessage":"","plotOptions":{"table":{"formatter":[]},"map":{"geoData":{}}},"source":{"dataType":"lazy","lazyData":[]},"guide":{"message":"Set data options using Chart Setting Button."}},"dataSource":{"selectable":true},"style":{},"group":"rg4q2dvkdkn6bf9emtrgxq3h"}],"layout":{"type":"panel","id":"default-1546850645288"}}],"full":[{"panel":[],"layout":{}}]},"out":{"partial":[{"panel":[{"id":"default-1546850645406","chartOption":{"colorSet":["#FD026C","#4682B8","#A5D22D","#F5CC0A","#FE8C01","#6B9494","#B97C46","#84ACD0","#C2E173","#F9DD5B","#FE569D","#FEB356","#9CB8B8","#D0A884","#2E6072","#6D8C1E","#A48806","#A90148","#A95E01","#476363","#7B532F"],"title":{"show":true,"text":"","subtext":"","rotate":0,"textStyle":{"color":"#000000","fontSize":12,"fontFamily":""},"subtextStyle":{"color":"#000000","fontSize":12,"fontFamily":""},"left":"50%","top":"0px"},"toolbar":{"show":false,"right":"8px","top":"8px","orientation":"horizontal","menu":{}},"chart":{"border":"1px #000000 none","background":"rgba(255, 255, 255,1)","animationDuration":1000,"type":"table"},"tooltip":{"triggerOn":"mousemove"},"grid":{"left":"10%","right":"10%","top":"60px","bottom":"60px","width":"auto","height":"auto"},"xAxis":[{"selected":[],"title":{"show":true,"text":"","subtext":"","rotate":0,"textStyle":{"color":"#000000","fontSize":12,"fontFamily":""},"subtextStyle":{"color":"#000000","fontSize":12,"fontFamily":""},"left":"50%","bottom":"5px"},"axisTick":{"show":true},"axisLine":{"onZero":false},"scale":true,"axisLabel":{"show":true,"rotate":0,"textStyle":{"color":"#000000","fontSize":12,"fontFamily":""}},"zlevel":1}],"yAxis":[{"selected":[],"title":{"show":true,"text":"","subtext":"","rotate":-90,"textStyle":{"color":"#000000","fontSize":12,"fontFamily":""},"subtextStyle":{"color":"#000000","fontSize":12,"fontFamily":""},"left":"8px","top":"50%"},"axisTick":{"show":true},"axisLine":{"onZero":false},"scale":true,"axisLabel":{"show":true,"rotate":0,"textStyle":{"color":"#000000","fontSize":12,"fontFamily":""}},"zlevel":1}],"colorBy":[{"selected":[]}],"legend":{"show":true,"orientation":"horizontal","left":"50%","right":"auto","top":"10px","bottom":"auto","textStyle":{"color":"#000000","fontSize":12,"fontFamily":"","fontStyle":"normal","fontWeight":"normal","fontDecoration":"none"}},"noDataMessage":"","plotOptions":{"table":{"formatter":[]},"map":{"geoData":{}}},"source":{"dataType":"lazy","lazyData":[]},"guide":{"message":"Set data options using Chart Setting Button."}},"dataSource":{"selectable":true},"style":{},"group":"dvx8aitcvwernigfcfnv6bmm"}],"layout":{"type":"panel","id":"default-1546850645406"}}],"full":[{"panel":[],"layout":{}}]}}},"fid":"fzapa6g2e2v5mdy6"},{"persist-mode":"auto","func":"brightics.function.transform$get_tabletable","name":"brightics.function.transform$get_table","param":{"key_list":["summary1"],"index_column_name":"variable","index_column":true},"display":{"label":"Get Table","diagram":{"position":{"x":1020,"y":120}},"sheet":{"in":{"partial":[{"panel":[],"layout":{}}],"full":[{"panel":[],"layout":{}}]},"out":{"partial":[{"panel":[{"id":"default-1546931066003","chartOption":{"colorSet":["#FD026C","#4682B8","#A5D22D","#F5CC0A","#FE8C01","#6B9494","#B97C46","#84ACD0","#C2E173","#F9DD5B","#FE569D","#FEB356","#9CB8B8","#D0A884","#2E6072","#6D8C1E","#A48806","#A90148","#A95E01","#476363","#7B532F"],"title":{"show":true,"text":"","subtext":"","rotate":0,"textStyle":{"color":"#000000","fontSize":12,"fontFamily":""},"subtextStyle":{"color":"#000000","fontSize":12,"fontFamily":""},"left":"50%","top":"0px"},"toolbar":{"show":false,"right":"8px","top":"8px","orientation":"horizontal","menu":{}},"chart":{"border":"1px #000000 none","background":"rgba(255, 255, 255,1)","animationDuration":1000,"type":"table"},"tooltip":{"triggerOn":"mousemove"},"grid":{"left":"10%","right":"10%","top":"60px","bottom":"60px","width":"auto","height":"auto"},"xAxis":[{"selected":[],"title":{"show":true,"text":"","subtext":"","rotate":0,"textStyle":{"color":"#000000","fontSize":12,"fontFamily":""},"subtextStyle":{"color":"#000000","fontSize":12,"fontFamily":""},"left":"50%","bottom":"5px"},"axisTick":{"show":true},"axisLine":{"onZero":false},"scale":true,"axisLabel":{"show":true,"rotate":0,"textStyle":{"color":"#000000","fontSize":12,"fontFamily":""}},"zlevel":1}],"yAxis":[{"selected":[],"title":{"show":true,"text":"","subtext":"","rotate":-90,"textStyle":{"color":"#000000","fontSize":12,"fontFamily":""},"subtextStyle":{"color":"#000000","fontSize":12,"fontFamily":""},"left":"8px","top":"50%"},"axisTick":{"show":true},"axisLine":{"onZero":false},"scale":true,"axisLabel":{"show":true,"rotate":0,"textStyle":{"color":"#000000","fontSize":12,"fontFamily":""}},"zlevel":1}],"colorBy":[{"selected":[]}],"legend":{"show":true,"orientation":"horizontal","left":"50%","right":"auto","top":"10px","bottom":"auto","textStyle":{"color":"#000000","fontSize":12,"fontFamily":"","fontStyle":"normal","fontWeight":"normal","fontDecoration":"none"}},"noDataMessage":"","plotOptions":{"table":{"formatter":[]},"map":{"geoData":{}}},"source":{"dataType":"lazy","lazyData":[]},"guide":{"message":"Set data options using Chart Setting Button."}},"dataSource":{"selectable":true},"style":{},"group":"hxp8eiex9u4ksr32cr7ae8pc"}],"layout":{"type":"panel","id":"default-1546931066003"}}],"full":[{"panel":[],"layout":{}}]}}},"meta":{"model":{"type":"model"},"table":{"type":"table"}},"context":"python","version":"3.6","inputs":{"model":"tb7bcjtdccw8x929"},"outputs":{"table":"te26927p4xgdzj6p"},"fid":"fxv2wbhretb86tb5"},{"persist-mode":"auto","func":"brightics.function.statistics$statistic_summary80870","name":"brightics.function.statistics$statistic_summary","param":{"input_cols":["on"],"group_by":["sensor","hour","dayofweek"],"statistics":["avg","median"]},"display":{"label":"Statistic Summary","diagram":{"position":{"x":770,"y":20}},"sheet":{"in":{"partial":[{"panel":[{"id":"default-1546934084513","chartOption":{"colorSet":["#FD026C","#4682B8","#A5D22D","#F5CC0A","#FE8C01","#6B9494","#B97C46","#84ACD0","#C2E173","#F9DD5B","#FE569D","#FEB356","#9CB8B8","#D0A884","#2E6072","#6D8C1E","#A48806","#A90148","#A95E01","#476363","#7B532F"],"title":{"show":true,"text":"","subtext":"","rotate":0,"textStyle":{"color":"#000000","fontSize":12,"fontFamily":""},"subtextStyle":{"color":"#000000","fontSize":12,"fontFamily":""},"left":"50%","top":"0px"},"toolbar":{"show":false,"right":"8px","top":"8px","orientation":"horizontal","menu":{}},"chart":{"border":"1px #000000 none","background":"rgba(255, 255, 255,1)","animationDuration":1000,"type":"table"},"tooltip":{"triggerOn":"mousemove"},"grid":{"left":"10%","right":"10%","top":"60px","bottom":"60px","width":"auto","height":"auto"},"xAxis":[{"selected":[],"title":{"show":true,"text":"","subtext":"","rotate":0,"textStyle":{"color":"#000000","fontSize":12,"fontFamily":""},"subtextStyle":{"color":"#000000","fontSize":12,"fontFamily":""},"left":"50%","bottom":"5px"},"axisTick":{"show":true},"axisLine":{"onZero":false},"scale":true,"axisLabel":{"show":true,"rotate":0,"textStyle":{"color":"#000000","fontSize":12,"fontFamily":""}},"zlevel":1}],"yAxis":[{"selected":[],"title":{"show":true,"text":"","subtext":"","rotate":-90,"textStyle":{"color":"#000000","fontSize":12,"fontFamily":""},"subtextStyle":{"color":"#000000","fontSize":12,"fontFamily":""},"left":"8px","top":"50%"},"axisTick":{"show":true},"axisLine":{"onZero":false},"scale":true,"axisLabel":{"show":true,"rotate":0,"textStyle":{"color":"#000000","fontSize":12,"fontFamily":""}},"zlevel":1}],"colorBy":[{"selected":[]}],"legend":{"show":true,"orientation":"horizontal","left":"50%","right":"auto","top":"10px","bottom":"auto","textStyle":{"color":"#000000","fontSize":12,"fontFamily":"","fontStyle":"normal","fontWeight":"normal","fontDecoration":"none"}},"noDataMessage":"","plotOptions":{"table":{"formatter":[]},"map":{"geoData":{}}},"source":{"dataType":"lazy","lazyData":[]},"guide":{"message":"Set data options using Chart Setting Button."}},"dataSource":{"selectable":true},"style":{},"group":"tnen9fg43xzt9am3772aek4q"}],"layout":{"type":"panel","id":"default-1546934084513"}}],"full":[{"panel":[],"layout":{}}]},"out":{"partial":[{"panel":[{"id":"default-1546934084579","chartOption":{"colorSet":["#FD026C","#4682B8","#A5D22D","#F5CC0A","#FE8C01","#6B9494","#B97C46","#84ACD0","#C2E173","#F9DD5B","#FE569D","#FEB356","#9CB8B8","#D0A884","#2E6072","#6D8C1E","#A48806","#A90148","#A95E01","#476363","#7B532F"],"title":{"show":true,"text":"","subtext":"","rotate":0,"textStyle":{"color":"#000000","fontSize":12,"fontFamily":""},"subtextStyle":{"color":"#000000","fontSize":12,"fontFamily":""},"left":"50%","top":"0px"},"toolbar":{"show":false,"right":"8px","top":"8px","orientation":"horizontal","menu":{}},"chart":{"border":"1px #000000 none","background":"rgba(255, 255, 255,1)","animationDuration":1000,"type":"table"},"tooltip":{"triggerOn":"mousemove"},"grid":{"left":"10%","right":"10%","top":"60px","bottom":"60px","width":"auto","height":"auto"},"xAxis":[{"selected":[],"title":{"show":true,"text":"","subtext":"","rotate":0,"textStyle":{"color":"#000000","fontSize":12,"fontFamily":""},"subtextStyle":{"color":"#000000","fontSize":12,"fontFamily":""},"left":"50%","bottom":"5px"},"axisTick":{"show":true},"axisLine":{"onZero":false},"scale":true,"axisLabel":{"show":true,"rotate":0,"textStyle":{"color":"#000000","fontSize":12,"fontFamily":""}},"zlevel":1}],"yAxis":[{"selected":[],"title":{"show":true,"text":"","subtext":"","rotate":-90,"textStyle":{"color":"#000000","fontSize":12,"fontFamily":""},"subtextStyle":{"color":"#000000","fontSize":12,"fontFamily":""},"left":"8px","top":"50%"},"axisTick":{"show":true},"axisLine":{"onZero":false},"scale":true,"axisLabel":{"show":true,"rotate":0,"textStyle":{"color":"#000000","fontSize":12,"fontFamily":""}},"zlevel":1}],"colorBy":[{"selected":[]}],"legend":{"show":true,"orientation":"horizontal","left":"50%","right":"auto","top":"10px","bottom":"auto","textStyle":{"color":"#000000","fontSize":12,"fontFamily":"","fontStyle":"normal","fontWeight":"normal","fontDecoration":"none"}},"noDataMessage":"","plotOptions":{"table":{"formatter":[]},"map":{"geoData":{}}},"source":{"dataType":"lazy","lazyData":[]},"guide":{"message":"Set data options using Chart Setting Button."}},"dataSource":{"selectable":true},"style":{},"group":"qryb9ehvs33x55btbkdxpne7"}],"layout":{"type":"panel","id":"default-1546934084579"}}],"full":[{"panel":[],"layout":{}}]}}},"meta":{"table":{"type":"table"},"out_table":{"type":"table"}},"context":"python","version":"3.6","inputs":{"table":"tkkpz2q8auj9y699"},"outputs":{"out_table":"tjqrht4awcweykkv"},"fid":"fyeh62c47n7mgzvg"},{"persist-mode":"auto","func":"addColumnPython","name":"brightics.function.extraction$add_expression_column","context":"python","version":"3.6","param":{"expr_type":"sqlite","new_cols":["feature"],"formulas":["replace(variable, 'mean__on__', '')"]},"inputs":{"table":"te26927p4xgdzj6p"},"outputs":{"out_table":"tee3zuvd8jc33mda"},"meta":{"table":{"type":"table"},"out_table":{"type":"table"}},"display":{"label":"Add Function Column","diagram":{"position":{"x":1270,"y":120}},"sheet":{"in":{"partial":[{"panel":[{"id":"default-1546934389106","chartOption":{"colorSet":["#FD026C","#4682B8","#A5D22D","#F5CC0A","#FE8C01","#6B9494","#B97C46","#84ACD0","#C2E173","#F9DD5B","#FE569D","#FEB356","#9CB8B8","#D0A884","#2E6072","#6D8C1E","#A48806","#A90148","#A95E01","#476363","#7B532F"],"title":{"show":true,"text":"","subtext":"","rotate":0,"textStyle":{"color":"#000000","fontSize":12,"fontFamily":""},"subtextStyle":{"color":"#000000","fontSize":12,"fontFamily":""},"left":"50%","top":"0px"},"toolbar":{"show":false,"right":"8px","top":"8px","orientation":"horizontal","menu":{}},"chart":{"border":"1px #000000 none","background":"rgba(255, 255, 255,1)","animationDuration":1000,"type":"table"},"tooltip":{"triggerOn":"mousemove"},"grid":{"left":"10%","right":"10%","top":"60px","bottom":"60px","width":"auto","height":"auto"},"xAxis":[{"selected":[],"title":{"show":true,"text":"","subtext":"","rotate":0,"textStyle":{"color":"#000000","fontSize":12,"fontFamily":""},"subtextStyle":{"color":"#000000","fontSize":12,"fontFamily":""},"left":"50%","bottom":"5px"},"axisTick":{"show":true},"axisLine":{"onZero":false},"scale":true,"axisLabel":{"show":true,"rotate":0,"textStyle":{"color":"#000000","fontSize":12,"fontFamily":""}},"zlevel":1}],"yAxis":[{"selected":[],"title":{"show":true,"text":"","subtext":"","rotate":-90,"textStyle":{"color":"#000000","fontSize":12,"fontFamily":""},"subtextStyle":{"color":"#000000","fontSize":12,"fontFamily":""},"left":"8px","top":"50%"},"axisTick":{"show":true},"axisLine":{"onZero":false},"scale":true,"axisLabel":{"show":true,"rotate":0,"textStyle":{"color":"#000000","fontSize":12,"fontFamily":""}},"zlevel":1}],"colorBy":[{"selected":[]}],"legend":{"show":true,"orientation":"horizontal","left":"50%","right":"auto","top":"10px","bottom":"auto","textStyle":{"color":"#000000","fontSize":12,"fontFamily":"","fontStyle":"normal","fontWeight":"normal","fontDecoration":"none"}},"noDataMessage":"","plotOptions":{"table":{"formatter":[]},"map":{"geoData":{}}},"source":{"dataType":"lazy","lazyData":[]},"guide":{"message":"Set data options using Chart Setting Button."}},"dataSource":{"selectable":true},"style":{},"group":"vd2winwif2a79n78x9u3tqaf"}],"layout":{"type":"panel","id":"default-1546934389106"}}],"full":[{"panel":[],"layout":{}}]},"out":{"partial":[{"panel":[{"id":"default-1546934389176","chartOption":{"colorSet":["#FD026C","#4682B8","#A5D22D","#F5CC0A","#FE8C01","#6B9494","#B97C46","#84ACD0","#C2E173","#F9DD5B","#FE569D","#FEB356","#9CB8B8","#D0A884","#2E6072","#6D8C1E","#A48806","#A90148","#A95E01","#476363","#7B532F"],"title":{"show":true,"text":"","subtext":"","rotate":0,"textStyle":{"color":"#000000","fontSize":12,"fontFamily":""},"subtextStyle":{"color":"#000000","fontSize":12,"fontFamily":""},"left":"50%","top":"0px"},"toolbar":{"show":false,"right":"8px","top":"8px","orientation":"horizontal","menu":{}},"chart":{"border":"1px #000000 none","background":"rgba(255, 255, 255,1)","animationDuration":1000,"type":"table"},"tooltip":{"triggerOn":"mousemove"},"grid":{"left":"10%","right":"10%","top":"60px","bottom":"60px","width":"auto","height":"auto"},"xAxis":[{"selected":[],"title":{"show":true,"text":"","subtext":"","rotate":0,"textStyle":{"color":"#000000","fontSize":12,"fontFamily":""},"subtextStyle":{"color":"#000000","fontSize":12,"fontFamily":""},"left":"50%","bottom":"5px"},"axisTick":{"show":true},"axisLine":{"onZero":false},"scale":true,"axisLabel":{"show":true,"rotate":0,"textStyle":{"color":"#000000","fontSize":12,"fontFamily":""}},"zlevel":1}],"yAxis":[{"selected":[],"title":{"show":true,"text":"","subtext":"","rotate":-90,"textStyle":{"color":"#000000","fontSize":12,"fontFamily":""},"subtextStyle":{"color":"#000000","fontSize":12,"fontFamily":""},"left":"8px","top":"50%"},"axisTick":{"show":true},"axisLine":{"onZero":false},"scale":true,"axisLabel":{"show":true,"rotate":0,"textStyle":{"color":"#000000","fontSize":12,"fontFamily":""}},"zlevel":1}],"colorBy":[{"selected":[]}],"legend":{"show":true,"orientation":"horizontal","left":"50%","right":"auto","top":"10px","bottom":"auto","textStyle":{"color":"#000000","fontSize":12,"fontFamily":"","fontStyle":"normal","fontWeight":"normal","fontDecoration":"none"}},"noDataMessage":"","plotOptions":{"table":{"formatter":[]},"map":{"geoData":{}}},"source":{"dataType":"lazy","lazyData":[]},"guide":{"message":"Set data options using Chart Setting Button."}},"dataSource":{"selectable":true},"style":{},"group":"a5nhuvnjijav54cksiprnppj"}],"layout":{"type":"panel","id":"default-1546934389176"}}],"full":[{"panel":[],"layout":{}}]}}},"fid":"fm6nxn34gvmyy36c"},{"persist-mode":"auto","func":"addColumnPython","name":"brightics.function.extraction$add_expression_column","context":"python","version":"3.6","param":{"expr_type":"sqlite","new_cols":["power_consumption"],"formulas":["coef * avg"]},"inputs":{"table":"t3c56c8ukavbqaks"},"outputs":{"out_table":"tpygrjfbhyhwtyp2"},"meta":{"table":{"type":"table"},"out_table":{"type":"table"}},"display":{"label":"Add Function Column","diagram":{"position":{"x":1770,"y":120}},"sheet":{"in":{"partial":[{"panel":[{"id":"default-1546934499215","chartOption":{"colorSet":["#FD026C","#4682B8","#A5D22D","#F5CC0A","#FE8C01","#6B9494","#B97C46","#84ACD0","#C2E173","#F9DD5B","#FE569D","#FEB356","#9CB8B8","#D0A884","#2E6072","#6D8C1E","#A48806","#A90148","#A95E01","#476363","#7B532F"],"title":{"show":true,"text":"","subtext":"","rotate":0,"textStyle":{"color":"#000000","fontSize":12,"fontFamily":""},"subtextStyle":{"color":"#000000","fontSize":12,"fontFamily":""},"left":"50%","top":"0px"},"toolbar":{"show":false,"right":"8px","top":"8px","orientation":"horizontal","menu":{}},"chart":{"border":"1px #000000 none","background":"rgba(255, 255, 255,1)","animationDuration":1000,"type":"table"},"tooltip":{"triggerOn":"mousemove"},"grid":{"left":"10%","right":"10%","top":"60px","bottom":"60px","width":"auto","height":"auto"},"xAxis":[{"selected":[],"title":{"show":true,"text":"","subtext":"","rotate":0,"textStyle":{"color":"#000000","fontSize":12,"fontFamily":""},"subtextStyle":{"color":"#000000","fontSize":12,"fontFamily":""},"left":"50%","bottom":"5px"},"axisTick":{"show":true},"axisLine":{"onZero":false},"scale":true,"axisLabel":{"show":true,"rotate":0,"textStyle":{"color":"#000000","fontSize":12,"fontFamily":""}},"zlevel":1}],"yAxis":[{"selected":[],"title":{"show":true,"text":"","subtext":"","rotate":-90,"textStyle":{"color":"#000000","fontSize":12,"fontFamily":""},"subtextStyle":{"color":"#000000","fontSize":12,"fontFamily":""},"left":"8px","top":"50%"},"axisTick":{"show":true},"axisLine":{"onZero":false},"scale":true,"axisLabel":{"show":true,"rotate":0,"textStyle":{"color":"#000000","fontSize":12,"fontFamily":""}},"zlevel":1}],"colorBy":[{"selected":[]}],"legend":{"show":true,"orientation":"horizontal","left":"50%","right":"auto","top":"10px","bottom":"auto","textStyle":{"color":"#000000","fontSize":12,"fontFamily":"","fontStyle":"normal","fontWeight":"normal","fontDecoration":"none"}},"noDataMessage":"","plotOptions":{"table":{"formatter":[]},"map":{"geoData":{}}},"source":{"dataType":"lazy","lazyData":[]},"guide":{"message":"Set data options using Chart Setting Button."}},"dataSource":{"selectable":true},"style":{},"group":"2vk97k8bmsbu4kv7bqx5byuh"}],"layout":{"type":"panel","id":"default-1546934499215"}}],"full":[{"panel":[],"layout":{}}]},"out":{"partial":[{"panel":[{"id":"default-1546934499284","chartOption":{"colorSet":["#FD026C","#4682B8","#A5D22D","#F5CC0A","#FE8C01","#6B9494","#B97C46","#84ACD0","#C2E173","#F9DD5B","#FE569D","#FEB356","#9CB8B8","#D0A884","#2E6072","#6D8C1E","#A48806","#A90148","#A95E01","#476363","#7B532F"],"title":{"show":true,"text":"","subtext":"","rotate":0,"textStyle":{"color":"#000000","fontSize":12,"fontFamily":""},"subtextStyle":{"color":"#000000","fontSize":12,"fontFamily":""},"left":"50%","top":"0px"},"toolbar":{"show":false,"right":"8px","top":"8px","orientation":"horizontal","menu":{"brush":{},"zoom":{"zoomAxis":"xAxis"}}},"chart":{"border":"1px #000000 none","background":"rgba(255, 255, 255,1)","animationDuration":1000,"type":"column"},"tooltip":{"triggerOn":"mousemove"},"grid":{"left":"10%","right":"10%","top":"60px","bottom":"60px","width":"auto","height":"auto"},"xAxis":[{"selected":[{"name":"hour","value":"hour","type":"String"}],"title":{"show":true,"text":"","subtext":"","rotate":0,"textStyle":{"color":"#000000","fontSize":12,"fontFamily":""},"subtextStyle":{"color":"#000000","fontSize":12,"fontFamily":""},"left":"50%","bottom":"5px"},"axisTick":{"show":true},"axisLine":{"onZero":false},"scale":true,"axisLabel":{"show":true,"rotate":0,"textStyle":{"color":"#000000","fontSize":12,"fontFamily":""}},"zlevel":1,"axisType":null}],"yAxis":[{"selected":[{"name":"power_consumption","aggregation":"sum","value":"power_consumption","type":"Double"}],"title":{"show":true,"text":"","subtext":"","rotate":-90,"textStyle":{"color":"#000000","fontSize":12,"fontFamily":""},"subtextStyle":{"color":"#000000","fontSize":12,"fontFamily":""},"left":"8px","top":"50%"},"axisTick":{"show":true},"axisLine":{"onZero":false},"scale":true,"axisLabel":{"show":true,"rotate":0,"textStyle":{"color":"#000000","fontSize":12,"fontFamily":""}},"zlevel":1,"axisType":null}],"colorBy":[{"selected":[{"value":"sensor","name":"sensor","type":"String"}],"axisType":null}],"legend":{"show":true,"orientation":"horizontal","left":"50%","right":"auto","top":"10px","bottom":"auto","textStyle":{"color":"#000000","fontSize":12,"fontFamily":"","fontStyle":"normal","fontWeight":"normal","fontDecoration":"none"}},"noDataMessage":"","plotOptions":{"column":{"stripLine":{"lineStyle":{"normal":{"color":"#000000","type":"solid","width":1}},"data":[{}]},"trendLine":{"lineStyle":{"normal":{"color":"#000000","type":"solid","width":1}},"data":[{}]},"tooltip":{"trigger":"item"}},"table":{"formatter":[]},"map":{"geoData":{}}},"source":{"dataType":"lazy","lazyData":[]},"guide":{"message":"Set data options using Chart Setting Button."}},"dataSource":{"selectable":true},"style":{},"group":"fi9ra9bwu96wifwcmsr7vwr3"},{"id":"k556uhph","chartOption":{"colorSet":["#FD026C","#4682B8","#A5D22D","#F5CC0A","#FE8C01","#6B9494","#B97C46","#84ACD0","#C2E173","#F9DD5B","#FE569D","#FEB356","#9CB8B8","#D0A884","#2E6072","#6D8C1E","#A48806","#A90148","#A95E01","#476363","#7B532F"],"title":{"show":true,"text":"","subtext":"","rotate":0,"textStyle":{"color":"#000000","fontSize":12,"fontFamily":""},"subtextStyle":{"color":"#000000","fontSize":12,"fontFamily":""},"left":"50%","top":"0px"},"toolbar":{"show":false,"right":"8px","top":"8px","orientation":"horizontal","menu":{}},"chart":{"border":"1px #000000 none","background":"rgba(255, 255, 255,1)","animationDuration":1000,"type":"table"},"tooltip":{"triggerOn":"mousemove"},"grid":{"left":"10%","right":"10%","top":"60px","bottom":"60px","width":"auto","height":"auto"},"xAxis":[{"selected":[],"title":{"show":true,"text":"","subtext":"","rotate":0,"textStyle":{"color":"#000000","fontSize":12,"fontFamily":""},"subtextStyle":{"color":"#000000","fontSize":12,"fontFamily":""},"left":"50%","bottom":"5px"},"axisTick":{"show":true},"axisLine":{"onZero":false},"scale":true,"axisLabel":{"show":true,"rotate":0,"textStyle":{"color":"#000000","fontSize":12,"fontFamily":""}},"zlevel":1}],"yAxis":[{"selected":[],"title":{"show":true,"text":"","subtext":"","rotate":-90,"textStyle":{"color":"#000000","fontSize":12,"fontFamily":""},"subtextStyle":{"color":"#000000","fontSize":12,"fontFamily":""},"left":"8px","top":"50%"},"axisTick":{"show":true},"axisLine":{"onZero":false},"scale":true,"axisLabel":{"show":true,"rotate":0,"textStyle":{"color":"#000000","fontSize":12,"fontFamily":""}},"zlevel":1}],"colorBy":[{"selected":[]}],"legend":{"show":true,"orientation":"horizontal","left":"50%","right":"auto","top":"10px","bottom":"auto","textStyle":{"color":"#000000","fontSize":12,"fontFamily":"","fontStyle":"normal","fontWeight":"normal","fontDecoration":"none"}},"noDataMessage":"","plotOptions":{"table":{"formatter":[]},"map":{"geoData":{}}},"source":{"dataType":"lazy","lazyData":[]},"guide":{"message":"Set data options using Chart Setting Button."}},"dataSource":{"selectable":true},"style":{},"group":"fi9ra9bwu96wifwcmsr7vwr3"}],"layout":{"type":"splitter","direction":"horizontal","ratio":"29.521902967498818%","items":[{"id":"k556uhph","type":"panel"},{"id":"default-1546934499284","type":"panel"}]}}],"full":[{"panel":[],"layout":{}}]}}},"fid":"frr5s6jvv2jrv8e9"},{"persist-mode":"auto","context":"python","func":"merge","name":"brightics.function.transform$join","version":"3.6","inputs":{"left_table":"t47qszvdcvrpr5u8","right_table":"tdckugyuhjysm8y5"},"outputs":{"table":"twwmmdg9smr9fejs"},"meta":{"left_table":{"type":"table"},"right_table":{"type":"table"},"table":{"type":"table"}},"param":{"left_on":["timestamp"],"right_on":["time"],"how":"left","lsuffix":"","rsuffix":"","sort":"false"},"display":{"label":"Join","diagram":{"position":{"x":520,"y":120}},"sheet":{"in":{"partial":[{"panel":[{"id":"default-1548133865029","chartOption":{"colorSet":["#FD026C","#4682B8","#A5D22D","#F5CC0A","#FE8C01","#6B9494","#B97C46","#84ACD0","#C2E173","#F9DD5B","#FE569D","#FEB356","#9CB8B8","#D0A884","#2E6072","#6D8C1E","#A48806","#A90148","#A95E01","#476363","#7B532F"],"title":{"show":true,"text":"","subtext":"","rotate":0,"textStyle":{"color":"#000000","fontSize":12,"fontFamily":""},"subtextStyle":{"color":"#000000","fontSize":12,"fontFamily":""},"left":"50%","top":"0px"},"toolbar":{"show":false,"right":"8px","top":"8px","orientation":"horizontal","menu":{}},"chart":{"border":"1px #000000 none","background":"rgba(255, 255, 255,1)","animationDuration":1000,"type":"table"},"tooltip":{"triggerOn":"mousemove"},"grid":{"left":"10%","right":"10%","top":"60px","bottom":"60px","width":"auto","height":"auto"},"xAxis":[{"selected":[],"title":{"show":true,"text":"","subtext":"","rotate":0,"textStyle":{"color":"#000000","fontSize":12,"fontFamily":""},"subtextStyle":{"color":"#000000","fontSize":12,"fontFamily":""},"left":"50%","bottom":"5px"},"axisTick":{"show":true},"axisLine":{"onZero":false},"scale":true,"axisLabel":{"show":true,"rotate":0,"textStyle":{"color":"#000000","fontSize":12,"fontFamily":""}},"zlevel":1}],"yAxis":[{"selected":[],"title":{"show":true,"text":"","subtext":"","rotate":-90,"textStyle":{"color":"#000000","fontSize":12,"fontFamily":""},"subtextStyle":{"color":"#000000","fontSize":12,"fontFamily":""},"left":"8px","top":"50%"},"axisTick":{"show":true},"axisLine":{"onZero":false},"scale":true,"axisLabel":{"show":true,"rotate":0,"textStyle":{"color":"#000000","fontSize":12,"fontFamily":""}},"zlevel":1}],"colorBy":[{"selected":[]}],"legend":{"show":true,"orientation":"horizontal","left":"50%","right":"auto","top":"10px","bottom":"auto","textStyle":{"color":"#000000","fontSize":12,"fontFamily":"","fontStyle":"normal","fontWeight":"normal","fontDecoration":"none"}},"noDataMessage":"","plotOptions":{"table":{"formatter":[]},"map":{"geoData":{}}},"source":{"dataType":"lazy","lazyData":[]},"guide":{"message":"Set data options using Chart Setting Button."}},"dataSource":{"selectable":true},"style":{},"group":"jp62twzg253cqgxqmap4cvs5"}],"layout":{"type":"panel","id":"default-1548133865029"}}],"full":[{"panel":[],"layout":{}}]},"out":{"partial":[{"panel":[{"id":"default-1548133865102","chartOption":{"colorSet":["#FD026C","#4682B8","#A5D22D","#F5CC0A","#FE8C01","#6B9494","#B97C46","#84ACD0","#C2E173","#F9DD5B","#FE569D","#FEB356","#9CB8B8","#D0A884","#2E6072","#6D8C1E","#A48806","#A90148","#A95E01","#476363","#7B532F"],"title":{"show":true,"text":"","subtext":"","rotate":0,"textStyle":{"color":"#000000","fontSize":12,"fontFamily":""},"subtextStyle":{"color":"#000000","fontSize":12,"fontFamily":""},"left":"50%","top":"0px"},"toolbar":{"show":false,"right":"8px","top":"8px","orientation":"horizontal","menu":{}},"chart":{"border":"1px #000000 none","background":"rgba(255, 255, 255,1)","animationDuration":1000,"type":"table"},"tooltip":{"triggerOn":"mousemove"},"grid":{"left":"10%","right":"10%","top":"60px","bottom":"60px","width":"auto","height":"auto"},"xAxis":[{"selected":[],"title":{"show":true,"text":"","subtext":"","rotate":0,"textStyle":{"color":"#000000","fontSize":12,"fontFamily":""},"subtextStyle":{"color":"#000000","fontSize":12,"fontFamily":""},"left":"50%","bottom":"5px"},"axisTick":{"show":true},"axisLine":{"onZero":false},"scale":true,"axisLabel":{"show":true,"rotate":0,"textStyle":{"color":"#000000","fontSize":12,"fontFamily":""}},"zlevel":1}],"yAxis":[{"selected":[],"title":{"show":true,"text":"","subtext":"","rotate":-90,"textStyle":{"color":"#000000","fontSize":12,"fontFamily":""},"subtextStyle":{"color":"#000000","fontSize":12,"fontFamily":""},"left":"8px","top":"50%"},"axisTick":{"show":true},"axisLine":{"onZero":false},"scale":true,"axisLabel":{"show":true,"rotate":0,"textStyle":{"color":"#000000","fontSize":12,"fontFamily":""}},"zlevel":1}],"colorBy":[{"selected":[]}],"legend":{"show":true,"orientation":"horizontal","left":"50%","right":"auto","top":"10px","bottom":"auto","textStyle":{"color":"#000000","fontSize":12,"fontFamily":"","fontStyle":"normal","fontWeight":"normal","fontDecoration":"none"}},"noDataMessage":"","plotOptions":{"table":{"formatter":[]},"map":{"geoData":{}}},"source":{"dataType":"lazy","lazyData":[]},"guide":{"message":"Set data options using Chart Setting Button."}},"dataSource":{"selectable":true},"style":{},"group":"9k3mnruvn3b9jb5uewdt9ytq"}],"layout":{"type":"panel","id":"default-1548133865102"}}],"full":[{"panel":[],"layout":{}}]}}},"fid":"ftw8fn8wyfx4ysct"},{"persist-mode":"auto","func":"brightics.function.regression$linear_regression_train","name":"brightics.function.regression$linear_regression_train","param":{"fit_intercept":true,"is_vif":false,"feature_cols":["mean__on__AHU1","mean__on__AHU2","mean__on__AHU3","mean__on__BO1","mean__on__BO2","mean__on__CH1","mean__on__CH2"],"label_col":"value"},"display":{"label":"Linear Regression Train","diagram":{"position":{"x":770,"y":120}},"sheet":{"in":{"partial":[{"panel":[{"id":"default-1548133914706","chartOption":{"colorSet":["#FD026C","#4682B8","#A5D22D","#F5CC0A","#FE8C01","#6B9494","#B97C46","#84ACD0","#C2E173","#F9DD5B","#FE569D","#FEB356","#9CB8B8","#D0A884","#2E6072","#6D8C1E","#A48806","#A90148","#A95E01","#476363","#7B532F"],"title":{"show":true,"text":"","subtext":"","rotate":0,"textStyle":{"color":"#000000","fontSize":12,"fontFamily":""},"subtextStyle":{"color":"#000000","fontSize":12,"fontFamily":""},"left":"50%","top":"0px"},"toolbar":{"show":false,"right":"8px","top":"8px","orientation":"horizontal","menu":{}},"chart":{"border":"1px #000000 none","background":"rgba(255, 255, 255,1)","animationDuration":1000,"type":"table"},"tooltip":{"triggerOn":"mousemove"},"grid":{"left":"10%","right":"10%","top":"60px","bottom":"60px","width":"auto","height":"auto"},"xAxis":[{"selected":[],"title":{"show":true,"text":"","subtext":"","rotate":0,"textStyle":{"color":"#000000","fontSize":12,"fontFamily":""},"subtextStyle":{"color":"#000000","fontSize":12,"fontFamily":""},"left":"50%","bottom":"5px"},"axisTick":{"show":true},"axisLine":{"onZero":false},"scale":true,"axisLabel":{"show":true,"rotate":0,"textStyle":{"color":"#000000","fontSize":12,"fontFamily":""}},"zlevel":1}],"yAxis":[{"selected":[],"title":{"show":true,"text":"","subtext":"","rotate":-90,"textStyle":{"color":"#000000","fontSize":12,"fontFamily":""},"subtextStyle":{"color":"#000000","fontSize":12,"fontFamily":""},"left":"8px","top":"50%"},"axisTick":{"show":true},"axisLine":{"onZero":false},"scale":true,"axisLabel":{"show":true,"rotate":0,"textStyle":{"color":"#000000","fontSize":12,"fontFamily":""}},"zlevel":1}],"colorBy":[{"selected":[]}],"legend":{"show":true,"orientation":"horizontal","left":"50%","right":"auto","top":"10px","bottom":"auto","textStyle":{"color":"#000000","fontSize":12,"fontFamily":"","fontStyle":"normal","fontWeight":"normal","fontDecoration":"none"}},"noDataMessage":"","plotOptions":{"table":{"formatter":[]},"map":{"geoData":{}}},"source":{"dataType":"lazy","lazyData":[]},"guide":{"message":"Set data options using Chart Setting Button."}},"dataSource":{"selectable":true},"style":{},"group":"pajdxb2ygjteeh3b5pxhg6fc"}],"layout":{"type":"panel","id":"default-1548133914706"}}],"full":[{"panel":[],"layout":{}}]},"out":{"partial":[{"panel":[],"layout":{}}],"full":[{"panel":[],"layout":{}}]}}},"meta":{"table":{"type":"table"},"model":{"type":"model"}},"context":"python","version":"3.6","inputs":{"table":"twwmmdg9smr9fejs"},"outputs":{"model":"tb7bcjtdccw8x929"},"fid":"fxzc4mat5vz5rm3p"},{"persist-mode":"auto","context":"python","func":"merge","name":"brightics.function.transform$join","version":"3.6","inputs":{"left_table":"tjqrht4awcweykkv","right_table":"tee3zuvd8jc33mda"},"outputs":{"table":"t3c56c8ukavbqaks"},"meta":{"left_table":{"type":"table"},"right_table":{"type":"table"},"table":{"type":"table"}},"param":{"left_on":["sensor"],"right_on":["feature"],"how":"outer","lsuffix":"","rsuffix":"","sort":"false"},"display":{"label":"Join","diagram":{"position":{"x":1520,"y":120}},"sheet":{"in":{"partial":[{"panel":[{"id":"default-1548134602735","chartOption":{"colorSet":["#FD026C","#4682B8","#A5D22D","#F5CC0A","#FE8C01","#6B9494","#B97C46","#84ACD0","#C2E173","#F9DD5B","#FE569D","#FEB356","#9CB8B8","#D0A884","#2E6072","#6D8C1E","#A48806","#A90148","#A95E01","#476363","#7B532F"],"title":{"show":true,"text":"","subtext":"","rotate":0,"textStyle":{"color":"#000000","fontSize":12,"fontFamily":""},"subtextStyle":{"color":"#000000","fontSize":12,"fontFamily":""},"left":"50%","top":"0px"},"toolbar":{"show":false,"right":"8px","top":"8px","orientation":"horizontal","menu":{}},"chart":{"border":"1px #000000 none","background":"rgba(255, 255, 255,1)","animationDuration":1000,"type":"table"},"tooltip":{"triggerOn":"mousemove"},"grid":{"left":"10%","right":"10%","top":"60px","bottom":"60px","width":"auto","height":"auto"},"xAxis":[{"selected":[],"title":{"show":true,"text":"","subtext":"","rotate":0,"textStyle":{"color":"#000000","fontSize":12,"fontFamily":""},"subtextStyle":{"color":"#000000","fontSize":12,"fontFamily":""},"left":"50%","bottom":"5px"},"axisTick":{"show":true},"axisLine":{"onZero":false},"scale":true,"axisLabel":{"show":true,"rotate":0,"textStyle":{"color":"#000000","fontSize":12,"fontFamily":""}},"zlevel":1}],"yAxis":[{"selected":[],"title":{"show":true,"text":"","subtext":"","rotate":-90,"textStyle":{"color":"#000000","fontSize":12,"fontFamily":""},"subtextStyle":{"color":"#000000","fontSize":12,"fontFamily":""},"left":"8px","top":"50%"},"axisTick":{"show":true},"axisLine":{"onZero":false},"scale":true,"axisLabel":{"show":true,"rotate":0,"textStyle":{"color":"#000000","fontSize":12,"fontFamily":""}},"zlevel":1}],"colorBy":[{"selected":[]}],"legend":{"show":true,"orientation":"horizontal","left":"50%","right":"auto","top":"10px","bottom":"auto","textStyle":{"color":"#000000","fontSize":12,"fontFamily":"","fontStyle":"normal","fontWeight":"normal","fontDecoration":"none"}},"noDataMessage":"","plotOptions":{"table":{"formatter":[]},"map":{"geoData":{}}},"source":{"dataType":"lazy","lazyData":[]},"guide":{"message":"Set data options using Chart Setting Button."}},"dataSource":{"selectable":true},"style":{},"group":"pethcxwttiu4v4gjzmiem2gw"}],"layout":{"type":"panel","id":"default-1548134602735"}}],"full":[{"panel":[],"layout":{}}]},"out":{"partial":[{"panel":[{"id":"default-1548134602803","chartOption":{"colorSet":["#FD026C","#4682B8","#A5D22D","#F5CC0A","#FE8C01","#6B9494","#B97C46","#84ACD0","#C2E173","#F9DD5B","#FE569D","#FEB356","#9CB8B8","#D0A884","#2E6072","#6D8C1E","#A48806","#A90148","#A95E01","#476363","#7B532F"],"title":{"show":true,"text":"","subtext":"","rotate":0,"textStyle":{"color":"#000000","fontSize":12,"fontFamily":""},"subtextStyle":{"color":"#000000","fontSize":12,"fontFamily":""},"left":"50%","top":"0px"},"toolbar":{"show":false,"right":"8px","top":"8px","orientation":"horizontal","menu":{}},"chart":{"border":"1px #000000 none","background":"rgba(255, 255, 255,1)","animationDuration":1000,"type":"table"},"tooltip":{"triggerOn":"mousemove"},"grid":{"left":"10%","right":"10%","top":"60px","bottom":"60px","width":"auto","height":"auto"},"xAxis":[{"selected":[],"title":{"show":true,"text":"","subtext":"","rotate":0,"textStyle":{"color":"#000000","fontSize":12,"fontFamily":""},"subtextStyle":{"color":"#000000","fontSize":12,"fontFamily":""},"left":"50%","bottom":"5px"},"axisTick":{"show":true},"axisLine":{"onZero":false},"scale":true,"axisLabel":{"show":true,"rotate":0,"textStyle":{"color":"#000000","fontSize":12,"fontFamily":""}},"zlevel":1}],"yAxis":[{"selected":[],"title":{"show":true,"text":"","subtext":"","rotate":-90,"textStyle":{"color":"#000000","fontSize":12,"fontFamily":""},"subtextStyle":{"color":"#000000","fontSize":12,"fontFamily":""},"left":"8px","top":"50%"},"axisTick":{"show":true},"axisLine":{"onZero":false},"scale":true,"axisLabel":{"show":true,"rotate":0,"textStyle":{"color":"#000000","fontSize":12,"fontFamily":""}},"zlevel":1}],"colorBy":[{"selected":[]}],"legend":{"show":true,"orientation":"horizontal","left":"50%","right":"auto","top":"10px","bottom":"auto","textStyle":{"color":"#000000","fontSize":12,"fontFamily":"","fontStyle":"normal","fontWeight":"normal","fontDecoration":"none"}},"noDataMessage":"","plotOptions":{"table":{"formatter":[]},"map":{"geoData":{}}},"source":{"dataType":"lazy","lazyData":[]},"guide":{"message":"Set data options using Chart Setting Button."}},"dataSource":{"selectable":true},"style":{},"group":"5dwa9njbqwafvwykr3vphy6r"}],"layout":{"type":"panel","id":"default-1548134602803"}}],"full":[{"panel":[],"layout":{}}]}}},"fid":"fega4p2jyf6d26tp"},{"persist-mode":"auto","func":"addFunctionColumnsPython","name":"brightics.function.transform$sql_execute","context":"python","version":"3.6","param":{"query":"SELECT *, \nstrftime('%w',timestamp) as `dayofweek`, \nstrftime('%H',timestamp) as `hour`\nFROM #{DF(0)}"},"inputs":{"tables":"tcycsgn8gbatwm2d"},"outputs":{"out_table":"tkkpz2q8auj9y699"},"meta":{"tables":{"type":"table"},"out_table":{"type":"table"}},"display":{"label":"Add Function Columns","diagram":{"position":{"x":520,"y":20}},"sheet":{"in":{"partial":[{"panel":[{"id":"default-1554357853808","chartOption":{"colorSet":["#FD026C","#4682B8","#A5D22D","#F5CC0A","#FE8C01","#6B9494","#B97C46","#84ACD0","#C2E173","#F9DD5B","#FE569D","#FEB356","#9CB8B8","#D0A884","#2E6072","#6D8C1E","#A48806","#A90148","#A95E01","#476363","#7B532F"],"title":{"show":true,"text":"","subtext":"","rotate":0,"textStyle":{"color":"#000000","fontSize":12,"fontFamily":""},"subtextStyle":{"color":"#000000","fontSize":12,"fontFamily":""},"left":"50%","top":"0px"},"toolbar":{"show":false,"right":"8px","top":"8px","orientation":"horizontal","menu":{}},"chart":{"border":"1px #000000 none","background":"rgba(255, 255, 255,1)","animationDuration":1000,"type":"table"},"tooltip":{"triggerOn":"mousemove"},"grid":{"left":"10%","right":"10%","top":"60px","bottom":"60px","width":"auto","height":"auto"},"xAxis":[{"selected":[],"title":{"show":true,"text":"","subtext":"","rotate":0,"textStyle":{"color":"#000000","fontSize":12,"fontFamily":""},"subtextStyle":{"color":"#000000","fontSize":12,"fontFamily":""},"left":"50%","bottom":"5px"},"axisTick":{"show":true},"axisLine":{"onZero":false},"scale":true,"axisLabel":{"show":true,"rotate":0,"textStyle":{"color":"#000000","fontSize":12,"fontFamily":""}},"zlevel":1}],"yAxis":[{"selected":[],"title":{"show":true,"text":"","subtext":"","rotate":-90,"textStyle":{"color":"#000000","fontSize":12,"fontFamily":""},"subtextStyle":{"color":"#000000","fontSize":12,"fontFamily":""},"left":"8px","top":"50%"},"axisTick":{"show":true},"axisLine":{"onZero":false},"scale":true,"axisLabel":{"show":true,"rotate":0,"textStyle":{"color":"#000000","fontSize":12,"fontFamily":""}},"zlevel":1}],"colorBy":[{"selected":[]}],"legend":{"show":true,"orientation":"horizontal","left":"50%","right":"auto","top":"10px","bottom":"auto","textStyle":{"color":"#000000","fontSize":12,"fontFamily":"","fontStyle":"normal","fontWeight":"normal","fontDecoration":"none"}},"noDataMessage":"","plotOptions":{"table":{"formatter":[]},"map":{"geoData":{}}},"source":{"dataType":"lazy","lazyData":[]},"guide":{"message":"Set data options using Chart Setting Button."}},"dataSource":{"selectable":true},"style":{},"group":"nd5juhsjvukuixd6vp427a8i"}],"layout":{"type":"panel","id":"default-1554357853808"}}],"full":[{"panel":[],"layout":{}}]},"out":{"partial":[{"panel":[{"id":"default-1554357853857","chartOption":{"colorSet":["#FD026C","#4682B8","#A5D22D","#F5CC0A","#FE8C01","#6B9494","#B97C46","#84ACD0","#C2E173","#F9DD5B","#FE569D","#FEB356","#9CB8B8","#D0A884","#2E6072","#6D8C1E","#A48806","#A90148","#A95E01","#476363","#7B532F"],"title":{"show":true,"text":"","subtext":"","rotate":0,"textStyle":{"color":"#000000","fontSize":12,"fontFamily":""},"subtextStyle":{"color":"#000000","fontSize":12,"fontFamily":""},"left":"50%","top":"0px"},"toolbar":{"show":false,"right":"8px","top":"8px","orientation":"horizontal","menu":{}},"chart":{"border":"1px #000000 none","background":"rgba(255, 255, 255,1)","animationDuration":1000,"type":"table"},"tooltip":{"triggerOn":"mousemove"},"grid":{"left":"10%","right":"10%","top":"60px","bottom":"60px","width":"auto","height":"auto"},"xAxis":[{"selected":[],"title":{"show":true,"text":"","subtext":"","rotate":0,"textStyle":{"color":"#000000","fontSize":12,"fontFamily":""},"subtextStyle":{"color":"#000000","fontSize":12,"fontFamily":""},"left":"50%","bottom":"5px"},"axisTick":{"show":true},"axisLine":{"onZero":false},"scale":true,"axisLabel":{"show":true,"rotate":0,"textStyle":{"color":"#000000","fontSize":12,"fontFamily":""}},"zlevel":1}],"yAxis":[{"selected":[],"title":{"show":true,"text":"","subtext":"","rotate":-90,"textStyle":{"color":"#000000","fontSize":12,"fontFamily":""},"subtextStyle":{"color":"#000000","fontSize":12,"fontFamily":""},"left":"8px","top":"50%"},"axisTick":{"show":true},"axisLine":{"onZero":false},"scale":true,"axisLabel":{"show":true,"rotate":0,"textStyle":{"color":"#000000","fontSize":12,"fontFamily":""}},"zlevel":1}],"colorBy":[{"selected":[]}],"legend":{"show":true,"orientation":"horizontal","left":"50%","right":"auto","top":"10px","bottom":"auto","textStyle":{"color":"#000000","fontSize":12,"fontFamily":"","fontStyle":"normal","fontWeight":"normal","fontDecoration":"none"}},"noDataMessage":"","plotOptions":{"table":{"formatter":[]},"map":{"geoData":{}}},"source":{"dataType":"lazy","lazyData":[]},"guide":{"message":"Set data options using Chart Setting Button."}},"dataSource":{"selectable":true},"style":{},"group":"xq8wzte8a2fyqy5u3652cvcw"}],"layout":{"type":"panel","id":"default-1554357853857"}}],"full":[{"panel":[],"layout":{}}]}}},"fid":"fnyd72s3cuc3v46d"}],"links":[{"kid":"kx3eutcu2kjwuawd","sourceFid":"fsrq3rteaup3j3w2","targetFid":"f7kjjwjnkqw2mcg2"},{"kid":"kf5gj8ybwuq4h3xp","sourceFid":"f6ufkxbgp48yr86y","targetFid":"fzapa6g2e2v5mdy6"},{"kid":"kehm4hzxzng66qx2","sourceFid":"fxv2wbhretb86tb5","targetFid":"fm6nxn34gvmyy36c"},{"kid":"k7ag9t9mv8bgg42s","sourceFid":"f7kjjwjnkqw2mcg2","targetFid":"ftw8fn8wyfx4ysct"},{"kid":"ky74fdysj43q4tj7","sourceFid":"fzapa6g2e2v5mdy6","targetFid":"ftw8fn8wyfx4ysct"},{"kid":"kdxc5rs3g4zavfxn","sourceFid":"ftw8fn8wyfx4ysct","targetFid":"fxzc4mat5vz5rm3p"},{"kid":"kwrd3786qhxwh62r","sourceFid":"fxzc4mat5vz5rm3p","targetFid":"fxv2wbhretb86tb5"},{"kid":"k84p75fe8mmvjwh2","sourceFid":"fega4p2jyf6d26tp","targetFid":"frr5s6jvv2jrv8e9"},{"kid":"k9pe55y4a76q5ewj","sourceFid":"fyeh62c47n7mgzvg","targetFid":"fega4p2jyf6d26tp"},{"kid":"k35ffcxtg87u5z84","sourceFid":"fm6nxn34gvmyy36c","targetFid":"fega4p2jyf6d26tp"},{"kid":"k88xcxww4s3feyf3","sourceFid":"fsrq3rteaup3j3w2","targetFid":"fnyd72s3cuc3v46d"},{"kid":"ktyvfn6ytddszyae","sourceFid":"fnyd72s3cuc3v46d","targetFid":"fyeh62c47n7mgzvg"}],"preferences":{},"variables":{},"variableRef":[],"innerModels":{},"inData":[],"outData":[],"sheets":[],"param":{},"report":{"data":[{"id":"default-1546851004414-table","type":"Chart","originData":{"options":{"id":"default-1546851004414","chartOption":{"colorSet":["#FD026C","#4682B8","#A5D22D","#F5CC0A","#FE8C01","#6B9494","#B97C46","#84ACD0","#C2E173","#F9DD5B","#FE569D","#FEB356","#9CB8B8","#D0A884","#2E6072","#6D8C1E","#A48806","#A90148","#A95E01","#476363","#7B532F"],"title":{"show":true,"text":"","subtext":"","rotate":0,"textStyle":{"color":"#000000","fontSize":12,"fontFamily":""},"subtextStyle":{"color":"#000000","fontSize":12,"fontFamily":""},"left":"50%","top":"0px"},"toolbar":{"show":false,"right":"8px","top":"8px","orientation":"horizontal","menu":{}},"chart":{"border":"1px #000000 none","background":"rgba(255, 255, 255,1)","animationDuration":1000,"type":"table"},"tooltip":{"triggerOn":"mousemove"},"grid":{"left":"10%","right":"10%","top":"60px","bottom":"60px","width":"auto","height":"auto"},"xAxis":[{"selected":[],"title":{"show":true,"text":"","subtext":"","rotate":0,"textStyle":{"color":"#000000","fontSize":12,"fontFamily":""},"subtextStyle":{"color":"#000000","fontSize":12,"fontFamily":""},"left":"50%","bottom":"5px"},"axisTick":{"show":true},"axisLine":{"onZero":false},"scale":true,"axisLabel":{"show":true,"rotate":0,"textStyle":{"color":"#000000","fontSize":12,"fontFamily":""}},"zlevel":1}],"yAxis":[{"selected":[],"title":{"show":true,"text":"","subtext":"","rotate":-90,"textStyle":{"color":"#000000","fontSize":12,"fontFamily":""},"subtextStyle":{"color":"#000000","fontSize":12,"fontFamily":""},"left":"8px","top":"50%"},"axisTick":{"show":true},"axisLine":{"onZero":false},"scale":true,"axisLabel":{"show":true,"rotate":0,"textStyle":{"color":"#000000","fontSize":12,"fontFamily":""}},"zlevel":1}],"colorBy":[{"selected":[]}],"legend":{"show":true,"orientation":"horizontal","left":"50%","right":"auto","top":"10px","bottom":"auto","textStyle":{"color":"#000000","fontSize":12,"fontFamily":"","fontStyle":"normal","fontWeight":"normal","fontDecoration":"none"}},"noDataMessage":"","plotOptions":{"table":{"formatter":[]},"map":{"geoData":{}}},"source":{"dataType":"lazy","lazyData":[{"id":{"value":"t7g9nrw9pgptebgm","label":"Flatten Json"}}]},"guide":{"message":"Set data options using Chart Setting Button."}}},"data":{"mid":"msck6knz5vjh9w5j","fid":"fnyd72s3cuc3v46d"},"title":{"fnUnitLabel":"Flatten Json","panelTitle":""}}},{"id":"default-1546934499284-column","type":"Chart","originData":{"options":{"id":"default-1546934499284","chartOption":{"colorSet":["#FD026C","#4682B8","#A5D22D","#F5CC0A","#FE8C01","#6B9494","#B97C46","#84ACD0","#C2E173","#F9DD5B","#FE569D","#FEB356","#9CB8B8","#D0A884","#2E6072","#6D8C1E","#A48806","#A90148","#A95E01","#476363","#7B532F"],"title":{"show":true,"text":"","subtext":"","rotate":0,"textStyle":{"color":"#000000","fontSize":12,"fontFamily":""},"subtextStyle":{"color":"#000000","fontSize":12,"fontFamily":""},"left":"50%","top":"0px"},"toolbar":{"show":false,"right":"8px","top":"8px","orientation":"horizontal","menu":{"brush":{},"zoom":{"zoomAxis":"xAxis"}}},"chart":{"border":"1px #000000 none","background":"rgba(255, 255, 255,1)","animationDuration":1000,"type":"column"},"tooltip":{"triggerOn":"mousemove"},"grid":{"left":"10%","right":"10%","top":"60px","bottom":"60px","width":"auto","height":"auto"},"xAxis":[{"selected":[{"name":"sensor"}],"title":{"show":true,"text":"","subtext":"","rotate":0,"textStyle":{"color":"#000000","fontSize":12,"fontFamily":""},"subtextStyle":{"color":"#000000","fontSize":12,"fontFamily":""},"left":"50%","bottom":"5px"},"axisTick":{"show":true},"axisLine":{"onZero":false},"scale":true,"axisLabel":{"show":true,"rotate":0,"textStyle":{"color":"#000000","fontSize":12,"fontFamily":""}},"zlevel":1}],"yAxis":[{"selected":[{"name":"avg"}],"title":{"show":true,"text":"","subtext":"","rotate":-90,"textStyle":{"color":"#000000","fontSize":12,"fontFamily":""},"subtextStyle":{"color":"#000000","fontSize":12,"fontFamily":""},"left":"8px","top":"50%"},"axisTick":{"show":true},"axisLine":{"onZero":false},"scale":true,"axisLabel":{"show":true,"rotate":0,"textStyle":{"color":"#000000","fontSize":12,"fontFamily":""}},"zlevel":1}],"colorBy":[{"selected":[]}],"legend":{"show":true,"orientation":"horizontal","left":"50%","right":"auto","top":"10px","bottom":"auto","textStyle":{"color":"#000000","fontSize":12,"fontFamily":"","fontStyle":"normal","fontWeight":"normal","fontDecoration":"none"}},"noDataMessage":"","plotOptions":{"column":{"stripLine":{"lineStyle":{"normal":{"color":"#000000","type":"solid","width":1}},"data":[{}]},"trendLine":{"lineStyle":{"normal":{"color":"#000000","type":"solid","width":1}},"data":[{}]},"tooltip":{"trigger":"item"}},"table":{"formatter":[]},"map":{"geoData":{}}},"source":{"dataType":"lazy","lazyData":[{"id":{"value":"txfntq7tgxnmhwws","label":"Add Function Column"}}]},"guide":{"message":"Set data options using Chart Setting Button."}}},"data":{"mid":"msck6knz5vjh9w5j","fid":"fnyd72s3cuc3v46d","table":"tpygrjfbhyhwtyp2"},"title":{"fnUnitLabel":"Add Function Column","panelTitle":""}}}],"title":"Report"},"persist-mode":"auto","diagram":{"PAPER_MARGIN_TOP":20,"PAPER_MARGIN_LEFT":20,"FIGURE_WIDTH":195,"FIGURE_HEIGHT":60,"GAP_WIDTH":55,"GAP_HEIGHT":40},"problemList":[]},"description":"","model_image":null,"creator":"brightics@samsung.com","create_time":"2019-08-08T06:42:41.000Z","updater":"brightics@samsung.com","update_time":"2019-08-08T08:56:05.000Z","event_key":"2019_085605.000","type":"data","tag":"null","from_version":"0.0"}}],"version":"3.6"}